easy_reed/__init__.py
easy_reed/_logger.py
easy_reed/config_object.py
easy_reed/config_reader.py
easy_reed/environment.py
easy_reed/namespace.py
easy_reed-0.9.2.dist-info/LICENSE.txt
easy_reed-0.9.2.dist-info/METADATA
easy_reed-0.9.2.dist-info/WHEEL
easy_reed-0.9.2.dist-info/top_level.txt
easy_reed-0.9.2.dist-info/RECORD
