Metadata-Version: 2.1
Name: easy_reed
Version: 0.9.2
Summary: Config Library for cross module configuration
Home-page: https://github.com/rns350/easy-reed
Author: Reed Schick
Author-email: rns350@nyu.edu
Requires-Python: >=3.7
License-File: LICENSE.txt
